quotehub/__init__.py
quotehub/quotehub.py
quotehub-0.3.dist-info/METADATA
quotehub-0.3.dist-info/WHEEL
quotehub-0.3.dist-info/top_level.txt
quotehub-0.3.dist-info/RECORD
