Metadata-Version: 2.1
Name: quotehub
Version: 0.3
